git_lines_graph/__init__.py
git_lines_graph-2.3.0.dist-info/METADATA
git_lines_graph-2.3.0.dist-info/WHEEL
git_lines_graph-2.3.0.dist-info/entry_points.txt
git_lines_graph-2.3.0.dist-info/licenses/LICENSE
git_lines_graph-2.3.0.dist-info/RECORD
