Metadata-Version: 2.4
Name: git-lines-graph
Version: 2.3.0
Summary: Git commit lines graph
Project-URL: Repository, https://github.com/danielfleischer/git-commits-lines-graph
Project-URL: Issues, https://github.com/danielfleischer/git-commits-lines-graph/issues
Project-URL: Homepage, https://github.com/danielfleischer/git-commits-lines-graph
Author: Daniel Fleischer
License-Expression: GPL-3.0-or-later
License-File: LICENSE
Keywords: commits,development,git,graph,visualization
Classifier: Development Status :: 5 - Production/Stable
Classifier: Intended Audience :: Developers
Classifier: License :: OSI Approved :: GNU General Public License v3 or later (GPLv3+)
Classifier: Operating System :: OS Independent
Classifier: Programming Language :: Python :: 3
Classifier: Programming Language :: Python :: 3.9
Classifier: Programming Language :: Python :: 3.10
Classifier: Programming Language :: Python :: 3.11
Classifier: Programming Language :: Python :: 3.12
Classifier: Topic :: Scientific/Engineering :: Visualization
Classifier: Topic :: Software Development :: Version Control :: Git
Requires-Python: >=3.9
Requires-Dist: gitpython>=3.1.43
Requires-Dist: matplotlib>=3.9.2
Requires-Dist: pandas>=2.2.2
